{"legislative_session": "69", "identifier": "SB 2403", "title": "AN ACT to amend and reenact section 6-09-47 of the North Dakota Century Code, relating to a medical facility emergency operating loan program under the medical facility infrastructure loan fund; to provide an appropriation; to provide a transfer; to provide an effective date; and to provide an expiration date.", "from_organization": "~{\"classification\": \"upper\"}", "classification": ["bill"], "subject": [], "abstracts": [{"note": "summary", "abstract": "Relating to a medical facility emergency operating loan program under the medical facility infrastructure loan fund; to provide an appropriation; to provide a transfer; to provide an effective date; and to provide an expiration date."}], "other_titles": [], "other_identifiers": [], "actions": [{"description": "Introduced, first reading, referred Joint Appropriations Committee", "date": "2026-01-21", "organization_id": "~{\"classification\": \"upper\"}", "classification": ["introduction"], "related_entities": []}, {"description": "Committee Hearing 02:30", "date": "2026-01-21", "organization_id": "~{\"classification\": \"upper\"}", "classification": [], "related_entities": []}, {"description": "Reported back amended, do pass, amendment placed on calendar 15 0 1", "date": "2026-01-22", "organization_id": "~{\"classification\": \"upper\"}", "classification": ["committee-passage", "committee-passage-favorable"], "related_entities": []}, {"description": "Amendment adopted, placed on calendar", "date": "2026-01-22", "organization_id": "~{\"classification\": \"upper\"}", "classification": [], "related_entities": []}, {"description": "Second reading, passed, yeas 46 nays 0", "date": "2026-01-22", "organization_id": "~{\"classification\": \"upper\"}", "classification": ["passage", "reading-2"], "related_entities": []}, {"description": "Received from Senate", "date": "2026-01-22", "organization_id": "~{\"classification\": \"lower\"}", "classification": [], "related_entities": []}, {"description": "Introduced, first reading, referred Joint Appropriations Committee", "date": "2026-01-22", "organization_id": "~{\"classification\": \"lower\"}", "classification": ["introduction"], "related_entities": []}, {"description": "Engrossment placed on calendar 22 0 1", "date": "2026-01-22", "organization_id": "~{\"classification\": \"lower\"}", "classification": [], "related_entities": []}, {"description": "Second reading, passed, yeas 80 nays 12", "date": "2026-01-23", "organization_id": "~{\"classification\": \"lower\"}", "classification": ["passage", "reading-2"], "related_entities": []}, {"description": "Returned to Senate", "date": "2026-01-23", "organization_id": "~{\"classification\": \"upper\"}", "classification": [], "related_entities": []}, {"description": "Signed by Speaker", "date": "2026-01-23", "organization_id": "~{\"classification\": \"lower\"}", "classification": [], "related_entities": []}, {"description": "Signed by President", "date": "2026-01-23", "organization_id": "~{\"classification\": \"upper\"}", "classification": [], "related_entities": []}, {"description": "Sent to Governor", "date": "2026-01-23", "organization_id": "~{\"classification\": \"upper\"}", "classification": ["executive-receipt"], "related_entities": []}, {"description": "Signed by Governor 01/23", "date": "2026-01-23", "organization_id": "~{\"classification\": \"upper\"}", "classification": ["executive-signature"], "related_entities": []}, {"description": "Filed with Secretary Of State 01/23", "date": "2026-01-28", "organization_id": "~{\"classification\": \"legislature\"}", "classification": ["introduction"], "related_entities": []}], "sponsorships": [{"name": "Donald Schaible", "classification": "primary", "entity_type": "person", "primary": true, "person_id": "~{\"chamber\": \"upper\", \"name\": \"Donald Schaible\"}", "organization_id": null}, {"name": "Dawson Holle", "classification": "cosponsor", "entity_type": "person", "primary": false, "person_id": "~{\"chamber\": \"lower\", \"name\": \"Dawson Holle\"}", "organization_id": null}, {"name": "Karen M. Rohr", "classification": "cosponsor", "entity_type": "person", "primary": false, "person_id": "~{\"chamber\": \"lower\", \"name\": \"Karen M. Rohr\"}", "organization_id": null}], "related_bills": [], "versions": [{"note": "INTRODUCED", "links": [{"url": "https://ndlegis.gov/assembly/69-2025/special/documents/25-1408-01000.pdf", "media_type": "application/pdf"}], "date": "", "classification": ""}, {"note": "FIRST ENGROSSMENT", "links": [{"url": "https://ndlegis.gov/assembly/69-2025/special/documents/25-1408-02000.pdf", "media_type": "application/pdf"}], "date": "", "classification": ""}, {"note": "Enrollment", "links": [{"url": "https://ndlegis.gov/assembly/69-2025/special/documents/25-1408-03000.pdf", "media_type": "application/pdf"}], "date": "", "classification": ""}], "documents": [{"note": "Prepared by the Legislative Council staff for Senator Bekkedahl", "links": [{"url": "https://ndlegis.gov/assembly/69-2025/special/documents/25-1408-01001m.pdf", "media_type": "application/pdf"}], "date": "", "classification": ""}], "citations": [], "sources": [{"url": "https://ndlegis.gov/assembly/69-2025/special/bill-overview/bo2403.html", "note": "HTML bill detail page"}, {"url": "https://ndlegis.gov/api/assembly/69-2025/data/bills.json", "note": "JSON page of session bills"}], "extras": {}, "jurisdiction": {"id": "ocd-jurisdiction/country:us/state:nd/government", "name": "North Dakota", "classification": "state", "division_id": "ocd-division/country:us/state:nd"}, "scraped_at": "2026-02-11T08:53:18+00:00", "_id": "1c8f28d8-0727-11f1-a34c-7e7240b0639d"}